playgroundrl/__init__.py
playgroundrl/actions.py
playgroundrl/args.py
playgroundrl/client.py
playgroundrl/state.py
playgroundrl/util.py
playgroundrl-0.1.2.dist-info/METADATA
playgroundrl-0.1.2.dist-info/WHEEL
playgroundrl-0.1.2.dist-info/top_level.txt
playgroundrl-0.1.2.dist-info/RECORD
