Metadata-Version: 2.1
Name: playgroundrl
Version: 0.1.2
Summary: Python SDK for Playground RL
Home-page: http://pypi.python.org/pypi/playgroundrl/
Author: Rayan Krishnan
Requires-Dist: python-socketio ==5.6.0
Requires-Dist: attrs ==22.2.0
Requires-Dist: cattrs ==22.2.0
